odoo/addons/website_sale_infinite_scroll/README.rst
odoo/addons/website_sale_infinite_scroll/__init__.py
odoo/addons/website_sale_infinite_scroll/__manifest__.py
odoo/addons/website_sale_infinite_scroll/controllers/__init__.py
odoo/addons/website_sale_infinite_scroll/controllers/main.py
odoo/addons/website_sale_infinite_scroll/demo/demo_products.xml
odoo/addons/website_sale_infinite_scroll/i18n/es.po
odoo/addons/website_sale_infinite_scroll/i18n/it.po
odoo/addons/website_sale_infinite_scroll/i18n/website_sale_infinite_scroll.pot
odoo/addons/website_sale_infinite_scroll/models/__init__.py
odoo/addons/website_sale_infinite_scroll/models/res_config_settings.py
odoo/addons/website_sale_infinite_scroll/models/website.py
odoo/addons/website_sale_infinite_scroll/readme/CONFIGURE.rst
odoo/addons/website_sale_infinite_scroll/readme/CONTRIBUTORS.rst
odoo/addons/website_sale_infinite_scroll/readme/DESCRIPTION.rst
odoo/addons/website_sale_infinite_scroll/readme/USAGE.rst
odoo/addons/website_sale_infinite_scroll/static/description/icon.png
odoo/addons/website_sale_infinite_scroll/static/description/index.html
odoo/addons/website_sale_infinite_scroll/static/src/js/bus_longpolling.js
odoo/addons/website_sale_infinite_scroll/static/src/js/main.js
odoo/addons/website_sale_infinite_scroll/static/src/js/widget_back_to_top.js
odoo/addons/website_sale_infinite_scroll/static/src/js/toors/toor.js
odoo/addons/website_sale_infinite_scroll/static/src/scss/main.scss
odoo/addons/website_sale_infinite_scroll/tests/__init__.py
odoo/addons/website_sale_infinite_scroll/tests/test_website_sale_infinite_scroll.py
odoo/addons/website_sale_infinite_scroll/views/assets.xml
odoo/addons/website_sale_infinite_scroll/views/res_config_settings.xml
odoo/addons/website_sale_infinite_scroll/views/templates.xml
odoo14_addon_website_sale_infinite_scroll-14.0.1.0.2.dist-info/METADATA
odoo14_addon_website_sale_infinite_scroll-14.0.1.0.2.dist-info/WHEEL
odoo14_addon_website_sale_infinite_scroll-14.0.1.0.2.dist-info/top_level.txt
odoo14_addon_website_sale_infinite_scroll-14.0.1.0.2.dist-info/RECORD
